{
  "jcr:primaryType": "cq:Page",
  "jcr:createdBy": "fireeye_global_admin",
  "jcr:created": "Tue May 05 2020 22:37:33 GMT+0000",
  "jcr:content": {
    "jcr:primaryType": "cq:PageContent",
    "jcr:mixinTypes": [
      "mix:versionable"
    ],
    "jcr:createdBy": "fireeye_global_admin",
    "jcr:title": "Ransomware gegen Industrieanlagen: Wie Hacker mit gezielten Angriffen auf IT- und OT-Systeme Produktionsprozesse unterbrechen",
    "jcr:versionHistory": "fb69f306-ac3e-4589-91fe-3ddf670750d3",
    "author": "Daniel Kapellmann Zafra",
    "cq:template": "\/apps\/fireeye-blog\/templates\/page_blogpost",
    "jcr:lastModifiedBy": "lynda.hall@fireeye.com",
    "jcr:language": "de_de",
    "jcr:predecessors": [
      "204f61fe-3263-4ce6-926f-5d009d4b4a1b"
    ],
    "jcr:created": "Mon Jul 27 2020 21:52:37 GMT+0000",
    "cq:lastModified": "Mon Jul 27 2020 21:52:34 GMT+0000",
    "jcr:baseVersion": "204f61fe-3263-4ce6-926f-5d009d4b4a1b",
    "jcr:isCheckedOut": true,
    "cq:tags": [
      "fireeye-blog-authors:daniel-kapellmann-zafra",
      "fireeye-blog-authors:keith-lunden",
      "fireeye-blog-authors:nathan-brubaker",
      "fireeye-blog-authors:jeremy-kennelly",
      "fireeye-blog-threat-research:threat-research",
      "fireeye-blog-tags:ics",
      "fireeye-blog-tags:homepage-carousel",
      "fireeye-blog-tags:latest",
      "fireeye-blog-tags:ransomware",
      "fireeye-blog-tags:cybercrime"
    ],
    "jcr:lastModified": "Tue May 05 2020 15:07:17 GMT+0000",
    "jcr:uuid": "326a8c03-19b2-45cc-9ab3-db87c0d15125",
    "sling:resourceType": "social\/blog\/components\/page",
    "published": "Mon Feb 24 2020 15:30:00 GMT-0800",
    "cq:lastModifiedBy": "reference-adjustment-service",
    "par": {
      "jcr:primaryType": "nt:unstructured",
      "sling:resourceType": "foundation\/components\/parsys",
      "entry": {
        "jcr:primaryType": "nt:unstructured",
        "jcr:lastModifiedBy": "lynda.hall@fireeye.com",
        "text": "\u003Cp\u003ESp\u00e4testens seit 2017 ist ein deutlicher Anstieg der Zahl der \u00f6ffentlich bekannt gewordenen Ransomware-Angriffe auf Industrieunternehmen und Betreiber kritischer Infrastrukturen zu verzeichnen. Infektionen mit prominenten Malware-Varianten wie WannaCry, LockerGoga, MegaCortex, Ryuk, Maze und seit Neuestem auch SNAKEHOSE (alias Snake bzw. Ekans) haben in vielen Branchen Kosten in Millionenh\u00f6he f\u00fcr L\u00f6segeldzahlungen und die Beseitigung der entstandenen Sch\u00e4den verursacht. Zudem ziehen diese Vorf\u00e4lle oft betr\u00e4chtliche St\u00f6rungen und Verz\u00f6gerungen der Produktion, Lieferung und Bereitstellung von G\u00fctern und Dienstleistungen nach sich.\u003C\/p\u003E\n\u003Cp\u003EDa in der \u00f6ffentlichen Diskussion des Themas meist die in der Presse verbreiteten Informationen \u00fcber die betroffenen Unternehmen und die unmittelbaren Auswirkungen auf bestimmte Industriezweige im Vordergrund stehen, verschwindet ein entscheidender Aspekt der j\u00fcngsten Ransomware-Angriffe aus dem Blickfeld: Unseren Beobachtungen zufolge wenden sich immer mehr finanziell motivierte Hackergruppen von opportunistischen Angriffstaktiken ab und setzen Ransomware erst nach der erfolgreichen Infiltration und sorgf\u00e4ltigen Aussp\u00e4hung einer Infrastruktur ein. Auf diese Weise werden gezielte Operationen gegen zentrale Systeme aus der Produktionskette m\u00f6glich. Die daraus resultierenden Ransomware-Infektionen beeintr\u00e4chtigen kritische Netzwerkressourcen oder in OT-Netzwerke eingebundene Computer oft so schwerwiegend, dass Produkte und Services nur in unzureichender Zahl oder mit gro\u00dfer Verz\u00f6gerung bereitgestellt werden k\u00f6nnen.\u003C\/p\u003E\n\u003Cp\u003EEine genaue Analyse dieser neuartigen Ransomware-Angriffe auf Industriebetriebe erfordert sowohl Expertenwissen als auch tiefgreifende Einblicke in IT- und OT-Systeme. Deshalb nutzen wir in diesem Beitrag die Erkenntnisse, die wir im Rahmen unserer Beratungst\u00e4tigkeit und bei unseren Bedrohungsstudien gewonnen haben, um den Wandel der auf Ransomware basierenden Angriffsmethoden und die dadurch m\u00f6glichen Unterbrechungen der industriellen Produktion genauer zu beleuchten.\u003C\/p\u003E\n\u003Ch4\u003EIndustriebetriebe sind zunehmend durch gezielte, erst nach dem ersten Eindringen erfolgende Ransomware-Angriffe gef\u00e4hrdet\u003C\/h4\u003E\n\u003Cp\u003EHerk\u00f6mmliche Ransomware-Angriffe basieren auf dem Gie\u00dfkannenprinzip und zielen darauf ab, eine gro\u00dfe Zahl von Unternehmen mit Malware zu infizieren, um L\u00f6segelder f\u00fcr verschl\u00fcsselte Dateien erpressen und sensible Daten stehlen zu k\u00f6nnen. Hier hoffen die Urheber darauf, von m\u00f6glichst vielen Betroffenen Zahlungen in einer durchschnittlichen H\u00f6he von 500 bis 1000 US-Dollar zu erhalten. Diese klassischen Kampagnen galten bisher kaum als Problem f\u00fcr die OT-Sicherheit, werden nun jedoch vermehrt durch im Rahmen komplexer Operationen erfolgende Ransomware-Angriffe auf bestimmte Industriebetriebe und Betreiber kritischer Infrastrukturen abgel\u00f6st.\u003C\/p\u003E\n\u003Cp\u003EDas bedeutet: Die Angreifer verschaffen sich beispielsweise mit breit gestreuter Malware Zugang zur Infrastruktur des anvisierten Unternehmens und konzentrieren sich nach dem ersten Eindringen zun\u00e4chst auf die Erlangung erweiterter Nutzerrechte, die Aussp\u00e4hung des Netzwerks und die Identifizierung kritischer Systeme, bevor sie ihre Ransomware einschleusen. Auf diese Weise k\u00f6nnen sie vermeiden, dass ihre Schadprogramme von sonst zuverl\u00e4ssig funktionierenden Sicherheitssystemen erkannt werden. Dar\u00fcber hinaus erm\u00f6glicht diese Vorgehensweise eine fl\u00e4chendeckende Infektion kritischer Systeme, sodass \u0026nbsp;die Angreifer das Ausma\u00df und die Durchschlagskraft ihrer Operationen maximieren k\u00f6nnen. Das bringt enorme Vorteile bei der Aushandlung von L\u00f6segeldern, deren H\u00f6he \u00fcblicherweise von den finanziellen Mitteln des betroffenen Unternehmens und dem Wert der mit Ransomware infizierten Ressourcen abh\u00e4ngt. (Weitere Informationen und ausf\u00fchrliche technische Details zu vergleichbaren Operationen finden Sie in unseren aktuellen Blogbeitr\u00e4gen \u00fcber Angriffe der Hackergruppen \u003Ca adhocenable=\u0022false\u0022 href=\u0022\/content\/fireeye-www\/en_US\/blog\/threat-research\/2019\/04\/pick-six-intercepting-a-fin6-intrusion.html\u0022\u003EFIN6\u003C\/a\u003E und \u003Ca adhocenable=\u0022false\u0022 href=\u0022\/content\/fireeye-www\/en_US\/blog\/threat-research\/2019\/01\/a-nasty-trick-from-credential-theft-malware-to-business-disruption.html\u0022\u003ETEMP.MixMaster\u003C\/a\u003E.)\u003C\/p\u003E\n\u003Cp\u003E\u003Cimg src=\u0022\/content\/dam\/fireeye-www\/blog\/images\/icsransomware\/Picture1.png\u0022 alt=\u0022\u0022\u003E\u003Cbr\u003E\n\u003Cspan class=\u0022type-XS\u0022\u003EAbbildung\u0026nbsp;1: Ransomware-Kampagnen nach dem Gie\u00dfkannenprinzip und gezielte Ransomware-Angriffe im Anschluss an einen bereits erfolgten Hackereinbruch im Vergleich\u003C\/span\u003E\u003C\/p\u003E\n\u003Cp\u003EFr\u00fcher erreichten die vorwiegend opportunistischen Ransomware-Kampagnen oft nur einzelne Computer \u2013 darunter gelegentlich auch \u00fcber das Internet zug\u00e4ngliche oder durch Wechselspeichermedien infizierte IT\/OT-Schnittstellensysteme. Doch seit 2017 beobachten wir zus\u00e4tzlich Angriffe mit wurmartigen Malware-Varianten wie NotPetya und BadRabbit, die speziell darauf ausgelegt sind, m\u00f6glichst viele Systeme eines Unternehmens zu infizieren und unwiderruflich zu l\u00f6schen (obwohl es sich vorgeblich um \u201enormale\u201c Ransomware handelt). Zu diesen beiden Gefahren kommen nun die oben angesprochenen gezielten Ransomware-Angriffe auf bereits zuvor infiltrierte Unternehmen, wodurch sich das Risiko f\u00fcr industrielle Produktionsprozesse auf dreierlei Weise erh\u00f6ht:\u003C\/p\u003E\n\u003Cul\u003E\n\u003Cli\u003EIm Zuge des \u00dcbergangs zu gezielten Angriffen geraten umsatzstarke Versorgungsbetriebe, Gesundheitsdienstleister und Fertigungsunternehmen zunehmend ins Visier finanziell motivierter Hacker, die sich die Tatsache zunutze machen, dass die betroffenen Firmen stark auf unterbrechungsfreie Betriebsprozesse angewiesen sind. Das bedeutet, dass nun neben Infrastrukturen zur Verarbeitung geldwerter Informationen (wie Kreditkarten- oder Kundendaten) auch industrielle Produktionsanlagen zum Ziel des kriminellen Profitstrebens werden.\u003C\/li\u003E\n\u003Cli\u003EDa die Hacker jede infiltrierte Infrastruktur zun\u00e4chst aussp\u00e4hen und weiter durchdringen, bevor sie ihre Ransomware einschleusen und verbreiten, k\u00f6nnen sie fl\u00e4chendeckend die wichtigsten Ressourcen des Zielunternehmens ins Visier nehmen und sich dadurch optimal f\u00fcr die anschlie\u00dfenden Verhandlungen \u00fcber L\u00f6segeldzahlungen positionieren.\u003C\/li\u003E\n\u003Cli\u003EIn der Vergangenheit wiesen viele der Taktiken, Techniken und Prozesse (TTP) finanziell motivierter Gruppen \u003Ca adhocenable=\u0022false\u0022 href=\u0022\/content\/fireeye-www\/en_US\/blog\/threat-research\/2019\/12\/fireeye-approach-to-operational-technology-security.html\u0022\u003Estarke \u00c4hnlichkeiten zur Vorgehensweise technisch extrem versierter Hacker\u003C\/a\u003E in den anf\u00e4nglichen und mittleren Phasen von Angriffen auf OT-Infrastrukturen auf. Deshalb ist es sehr wahrscheinlich, dass auch finanziell motivierte Angreifer in der Lage sind, in die als Bindeglied zwischen IT- und OT-Infrastruktur fungierenden Schnittstellensysteme einzudringen und von dort aus den Produktionsbetrieb mithilfe von Ransomware stark zu beeintr\u00e4chtigen.\u003C\/li\u003E\n\u003C\/ul\u003E\n\u003Ch4\u003EFinanziell motivierte Hackergruppen sind nachweislich in der Lage, OT-Ressourcen zu sabotieren\u003C\/h4\u003E\n\u003Cp\u003EHacker k\u00f6nnen mit gr\u00f6\u00dferer Wahrscheinlichkeit aus ihren Ransomware-Angriffen auf zuvor infiltrierte Infrastrukturen Kapital schlagen, wenn es ihnen gelingt, die gesch\u00e4ftskritischen Systeme des betroffenen Unternehmens lahmzulegen. Daher kann es nicht \u00fcberraschen, dass technisch versierte Kriminelle nicht mehr nur IT- und Gesch\u00e4ftsprozesse, sondern auch Kontroll- und \u00dcberwachungsprozesse in Produktionsanlagen ins Visier nehmen. Ausdruck dieses neuen Trends sind Malware-Varianten wie SNAKEHOUSE, die so designt sind, dass der eigentliche Schadcode erst nach der zwangsweisen Beendigung zahlreicher Prozesse ausgef\u00fchrt wird, wovon unter anderem die Industriesoftware von Anbietern wie General Electric und Honeywell betroffen ist. Die von SNAKEHOUSE verwendete Kill-Liste schien\u0026nbsp;auf den ersten Blick speziell auf OT-Umgebungen zugeschnitten zu sein, da unsere anf\u00e4nglichen Analysen mit automatisierten Tools zun\u00e4chst nur auf eine relativ kleine Zahl gr\u00f6\u00dftenteils betriebstechnischer Prozesse hinwiesen. Allerdings zeigte sich bei der manuellen Extraktion der Liste\u0026nbsp;, dass diese letztlich \u00fcber 1000 Prozesse umfasst.\u003C\/p\u003E\n\u003Cp\u003EDar\u00fcber hinaus stellten wir fest, dass es starke \u00dcberschneidungen mit den aus anderen Malware-Varianten wie LockerGoga, MegaCortex und Maze extrahierten Kill-Listen gibt. Und in der Tat wurden all diese Malware-Familien in den letzten zwei Jahren nachweislich bei schlagzeilentr\u00e4chtigen Angriffen auf Industriebetriebe eingesetzt. Bei der ersten von uns identifizierten Kill-Liste handelt es sich um eine Stapelverarbeitungsdatei, die im Zusammenhang mit LockerGoga im Januar 2019 verbreitet wurde. Diese Liste ist weitgehend mit den bei MegaCortex- oder SNAKEHOUSE-Infektionen vorgefundenen Kill-Listen identisch, weicht jedoch in einigen entscheidenden Punkten ab und unterscheidet sich unter anderem dadurch, dass sie den fehlerhaften Eintrag \u201eproficyclient.exe4\u201c enth\u00e4lt. Das Fehlen dieser Abweichung in SNAKEHOUSE und MegaCortex k\u00f6nnte darauf hindeuten, dass die Entwickler dieser Malware-Varianten den Fehler bemerkten und korrigierten, als sie die Liste der zu beendenden OT-Prozesse aus LockerGoga kopierten, oder dass der Programmierer von LockerGoga beim Import der Prozesse aus einer hypothetischen gemeinsamen Quelle im Darknet unachtsam war.\u003C\/p\u003E\n\u003Cp\u003E\u003Cimg src=\u0022\/content\/dam\/fireeye-www\/blog\/images\/icsransomware\/Picture2.png\u0022 alt=\u0022\u0022\u003E\u003Cbr\u003E\n\u003Cspan class=\u0022type-XS\u0022\u003EAbbildung 2: abweichende Schreibweise \u2013 der Eintrag \u201eproficyclient.exe\u201c in den Kill-Listen von LockerGoga (links) und SNAKEHOUS (rechts)\u003C\/span\u003E\u003C\/p\u003E\n\u003Cp\u003EAuch wenn es letztlich nur eine untergeordnete Rolle spielt, welche Ransomware-Familie zuerst OT-Prozesse in die eigene Kill-Liste aufgenommen hat, woher die Entwickler und Programmierer der einzelnen Malware-Varianten ihre Listen bezogen haben und ob die \u00c4hnlichkeiten zwischen den einzelnen Listen eventuell nur das Produkt \u00e4hnlicher Ergebnisse bei der Aussp\u00e4hung der Prozesse in verschiedenen Zielumgebungen sind, ist das\u0026nbsp;Vorhandensein einer in allen genannten F\u00e4llen\u0026nbsp;weitgehend einheitlichen Liste doch durchaus\u0026nbsp;bemerkenswert. Denn diese Liste er\u00f6ffnet finanziell motivierten Hackergruppen die M\u00f6glichkeit zur Sabotage von OT-Systemen und wird dadurch zum Fanal f\u00fcr weitere Angriffe auf industrielle Softwarel\u00f6sungen und Technologien, bei denen die Kriminellen ihre Kenntnisse \u00fcber OT-Umgebungen und das Zusammenspiel von IT- und OT-Infrastrukturen weiter ausbauen k\u00f6nnen.\u003C\/p\u003E\n\u003Ch4\u003ERansomware-Infektionen von IT- und OT-Systemen haben in der j\u00fcngsten Zeit zu Beeintr\u00e4chtigungen der industriellen Produktion gef\u00fchrt\u003C\/h4\u003E\n\u003Cp\u003EGetreu ihrer neuen Strategie ist es kriminellen Angreifern bereits verschiedentlich gelungen, Malware nach der erfolgreichen Infiltration einer Unternehmensinfrastruktur in IT- oder OT-Systeme einzuschleusen, um industrielle Produktionsprozesse zu st\u00f6ren. Bei diesen Ransomware-Angriffen wurden auf Servern und Computern gespeicherte Daten verschl\u00fcsselt, was die Funktionst\u00fcchtigkeit der zur Steuerung und \u00dcberwachung der Produktion genutzten OT-Netzwerke beeintr\u00e4chtigte. Die hieraus resultierenden Ausf\u00e4lle und Verz\u00f6gerungen bei der Bereitstellung von Produkten und Services zogen langfristige Verluste, verpasste Gesch\u00e4ftschancen, Geldstrafen und Imagesch\u00e4den nach sich und verursachten au\u00dferdem hohe Kosten f\u00fcr Incident-Response-Eins\u00e4tze und eventuelle L\u00f6segeldzahlungen. Dazu kommen eventuell noch negative Auswirkungen auf das gesellschaftliche Gemeinwohl, wenn Unternehmen aus der Versorgungsbranche oder dem \u00f6ffentlichen Sektor von Unterbrechungen betroffen sind.\u003C\/p\u003E\n\u003Cp\u003EDer wohl bekannteste derartige Vorfall ereignete sich im M\u00e4rz 2019, als das Prozessmanagementsystem des Unternehmens Norsk Hydro infolge einer Infektion des IT-Netzwerks zusammenbrach und die Einstellung des automatisierten Betriebs an verschiedenen Standorten erzwang. Hier unterbrach die eingesetzte Ransomware unter anderem den Informations- und Datenfluss zwischen den IT-Systemen f\u00fcr das Ressourcenmanagement in der gesamten Produktionskette. Dadurch wurde der Zugriff auf Produktbestandslisten unm\u00f6glich, sodass die Mitarbeiter die Verwaltung von mehr als 6500 Lagereinheiten und 4000 Regalen per Hand erledigen mussten. \u00c4hnliche Beobachtungen machten die Experten von FireEye Mandiant, die bei einem Incident-Response-Einsatz feststellten, dass die Angreifer den Trojaner TrickBot nutzten, um die Ransomware Ryuk in die IT-Infrastruktur eines Herstellers von \u00d6lbohrinseln einzuschleusen. In diesem Fall sorgte die \u00fcber interne Netzwerke fortschreitende Infektion f\u00fcr St\u00f6rungen der von Oracle bereitgestellten ERP-Software, die sowohl zeitweise Ausf\u00e4lle der Online-Pr\u00e4senz des Unternehmens als auch Produktionseinbu\u00dfen nach sich zogen.\u003C\/p\u003E\n\u003Cp\u003EDerlei Folgen sind bei allen Angriffen zu erwarten, bei denen die Benutzerschnittstellen von Maschinen oder Anlagen sowie industrielle Steuer- und Datenerfassungssysteme (Supervisory Control and Data Acquisition, SCADA), Engineering-Workstations und andere IT-basierte Ressourcen in OT-Netzwerken mit Ransomware infiziert werden. Denn viele dieser Technologien nutzen g\u00e4ngige Software und Standardbetriebssysteme, die f\u00fcr verschiedenste Bedrohungen anf\u00e4llig sind. Dem Team von Mandiant Intelligence ist mindestens ein Vorfall bekannt, bei dem eine Industrieanlage wegen eines massiven Ransomware-Angriffs vor\u00fcbergehend stillgelegt werden musste. Da die Infrastruktur des betreffenden Werks nicht ausreichend segmentiert war, konnte sich die Malware vom Unternehmensnetzwerk auf das OT-Netzwerk ausbreiten, wo sie zahlreiche Server, Benutzerschnittstellen, Workstations und Backups verschl\u00fcsselte. Der Produktionsbetrieb kam erst wieder in Gang, nachdem das Unternehmen mit gro\u00dfem Aufwand teils jahrzehntealte Backups von verschiedenen Anbietern angefordert hatte.\u003C\/p\u003E\n\u003Cp\u003EEin weiteres, j\u00fcngeres Beispiel vom Februar 2020 findet sich in der von der Cybersecurity Infrastructure and Security Agency (CISA) ver\u00f6ffentlichten Sicherheitswarnung \u003Ca href=\u0022https:\/\/www.us-cert.gov\/ncas\/alerts\/aa20-049a\u0022\u003EAA20-049A\u003C\/a\u003E, in der ein Hackereinbruch mit anschlie\u00dfendem Ransomware-Einsatz gegen die Kontroll- und Daten\u00fcbertragungssysteme im OT-Netzwerk einer Erdgasverdichterstation beschrieben wird. Wie dem Bericht zu entnehmen ist, waren hier Benutzeroberfl\u00e4chen, Datenerfassungssysteme und Polling-Server betroffen, was die Funktionst\u00fcchtigkeit der Station und die Kontrollm\u00f6glichkeiten der Betriebsingenieure stark einschr\u00e4nkte. In der Folge musste die Anlage kontrolliert heruntergefahren und f\u00fcr zwei komplette Tage au\u00dfer Betrieb genommen werden.\u003C\/p\u003E\n\u003Ch4\u003EZur Abwehr von Ransomware-Angriffen sind effektive Sicherheitsmechanismen in IT- und OT-Umgebungen erforderlich\u003C\/h4\u003E\n\u003Cp\u003EViele auf den Einsatz von Ransomware spezialisierte Angreifer sind zu einem hochgradig effektiven kriminellen Gesch\u00e4ftsmodell \u00fcbergegangen, das auf die Verursachung m\u00f6glichst kostspieliger Betriebsst\u00f6rungen abzielt. Deshalb fordern wir alle Unternehmen auf, die Sicherheit und Risiken ihrer industriellen Produktionsanlagen auch vor dem Hintergrund der neuesten Welle von Ransomware-Angriffen zu bewerten. Des Weiteren kann durch die Beachtung der unten aufgef\u00fchrten Empfehlungen der allgemeine Schutz gegen Ransomware und andere Bedrohungen der Betriebsprozesse (wie beispielsweise Krypto-Mining-Malware) gest\u00e4rkt werden. Diese Ratschl\u00e4ge gelten ungeachtet der Tatsache, dass jedes Unternehmen mit spezifischen Herausforderungen konfrontiert ist.\u003C\/p\u003E\n\u003Cp\u003EWenn Sie ma\u00dfgeschneiderte Services und n\u00fctzliche Bedrohungsdaten zum Schutz Ihrer IT- und OT-Umgebungen ben\u00f6tigen, sollten Sie die \u003Ca adhocenable=\u0022false\u0022 href=\u0022\/content\/fireeye-www\/de_DE\/mandiant\/incident-response.html\u0022\u003EBeratungsdienste von Mandiant\u003C\/a\u003E sowie die FireEye-Services \u003Ca adhocenable=\u0022false\u0022 href=\u0022\/content\/fireeye-www\/de_DE\/mandiant\/managed-detection-and-response.html\u0022\u003EManaged Defense\u003C\/a\u003E und \u003Ca adhocenable=\u0022false\u0022 href=\u0022\/content\/fireeye-www\/de_DE\/mandiant\/threat-intelligence.html\u0022\u003EThreat Intelligence\u003C\/a\u003E in Erw\u00e4gung ziehen.\u003C\/p\u003E\n\u003Cul\u003E\n\u003Cli\u003EF\u00fchren Sie Plan\u00fcbungen und\/oder Red-Team-Operationen durch, um die Effektivit\u00e4t Ihrer Sicherheitssysteme und -prozesse bei der Abwehr von Ransomware zu evaluieren. Dabei sollten Sie vor allem Angriffsszenarien w\u00e4hlen, die nicht schwerpunktm\u00e4\u00dfig auf Produktionsumgebungen fokussiert sind und gut dar\u00fcber Auskunft geben, wie gut (oder schlecht) Ihr Incident-Response-Team zur Erkennung, Untersuchung und Bek\u00e4mpfung eines solchen Angriffs sowie zur Wiederherstellung des Normalbetriebs in der Lage ist. Au\u00dferdem empfiehlt es sich, die Anforderungen an die Wiederherstellungsprozesse im Lichte der Ergebnisse der \u00dcbungen zu \u00fcberarbeiten. Generell ist davon auszugehen, dass das wiederholte Durchspielen verschiedener Bedrohungsszenarien das Sicherheitsbewusstsein der Mitarbeiter und die Reaktionsf\u00e4higkeit des Unternehmens insgesamt st\u00e4rkt.\u003C\/li\u003E\n\u003Cli\u003EAnalysieren Sie s\u00e4mtliche Unternehmensabl\u00e4ufe, Gesch\u00e4ftsprozesse und Workflows und identifizieren Sie jeweils die f\u00fcr die Aufrechterhaltung des Betriebs unerl\u00e4sslichen Ressourcen. Anschlie\u00dfend sollten Sie, wo dies m\u00f6glich ist, Redundanzen f\u00fcr kritische Systeme mit geringer Ausfalltoleranz einrichten, wobei Art und Umfang von den spezifischen, im Rahmen von Risiko- und Kosten-Nutzen-Analysen zu ermittelnden Anforderungen Ihres Unternehmens abh\u00e4ngen. Hierf\u00fcr m\u00fcssen neben den f\u00fcr die jeweiligen Prozesse Verantwortlichen auch alle IT- und OT-Teams einbezogen werden.\u003C\/li\u003E\n\u003Cli\u003EIsolieren Sie die in der Produktion genutzten Systeme mithilfe einer netzwerk- oder hostbasierten Firewall von den redundanten Ressourcen und st\u00e4rken Sie deren Schutz durch H\u00e4rtungsma\u00dfnahmen wie die Deaktivierung von SMB-, RDP- und WMI-Services und anderen oft zur Verbreitung von Ransomware genutzten Diensten. Zus\u00e4tzlich empfehlen wir die Implementierung von Richtlinien zur Unterbindung unn\u00f6tiger Peer-to-Peer- und Remote-Verbindungen sowie routinem\u00e4\u00dfige \u00dcberpr\u00fcfungen aller Systeme mit potenziell zur Verbreitung von Ransomware nutzbaren Services und Protokollen. Auf diese Weise k\u00f6nnen Sie Ihre Infrastruktur effektiver vor Sicherheitsverletzungen sch\u00fctzen.\u003C\/li\u003E\n\u003Cli\u003EBei der Implementierung robuster Backup-Prozesse sollten Sie besondere Ma\u00dfnahmen zur Sicherstellung der Datenintegrit\u00e4t ergreifen. Kritische Backups m\u00fcssen offline gespeichert werden oder sollten zumindest nur \u00fcber ein isoliertes Netzwerk zug\u00e4nglich sein.\u003C\/li\u003E\n\u003Cli\u003E\u00dcberarbeiten Sie die in Ihren Notfallpl\u00e4nen festgelegten\u0026nbsp;Zeitvorgaben f\u00fcr die Systemwiederherstellung und legen Sie alternative (gegebenenfalls auf manuellen Prozessen basierende) \u00dcberbr\u00fcckungs-Workflows fest. Dies ist besonders wichtig, wenn Ihr Unternehmen kritische Ressourcen nicht oder nur in begrenztem Ma\u00dfe durch Redundanzen sichern kann. Dar\u00fcber hinaus sollten Sie im Ernstfall darauf achten, sowohl die wiederhergestellten Ressourcen als auch die gesamte Infrastruktur Ihres Unternehmens zu h\u00e4rten, um wiederkehrende Ransomware-Infektionen zu vermeiden.\u003C\/li\u003E\n\u003Cli\u003ELegen Sie genau fest, wer f\u00fcr die Verwaltung der am OT-Perimeter implementierten Sicherheitsappliances zust\u00e4ndig ist, damit diese Systeme im Notfall schnell unternehmensweit angepasst werden k\u00f6nnen. Bei der Eind\u00e4mmung und Bek\u00e4mpfung eingedrungener Bedrohungen muss die Netzwerksegmentierung durchg\u00e4ngig aufrechterhalten werden.\u003C\/li\u003E\n\u003Cli\u003ESuchen Sie proaktiv nach Hinweisen auf Hackeraktivit\u00e4ten in \u003Ca adhocenable=\u0022false\u0022 href=\u0022\/content\/fireeye-www\/en_US\/blog\/threat-research\/2019\/12\/fireeye-approach-to-operational-technology-security.html\u0022\u003ESchnittstellensystemen\u003C\/a\u003E, die OT- und IT-Umgebungen miteinander verkn\u00fcpfen. Hierbei handelt es sich um in das Unternehmensnetzwerk eingebundene Workstations und Server, auf denen Standardbetriebssysteme und -protokolle laufen. Diese Systeme dienen zwar nicht der direkten Kontrolle der physischen Produktionsprozesse, werden jedoch h\u00e4ufig von auf Sabotage abzielenden Angreifern infiltriert und eignen sich daher gut als Objekt f\u00fcr vorbeugende Untersuchungen.\u003C\/li\u003E\n\u003Cli\u003EHalten Sie sich vor Augen, dass jedes Unternehmen \u00fcber eigene interne Infrastrukturen und Prozesse verf\u00fcgt und mit spezifischen Anforderungen von Stakeholdern und Kunden konfrontiert ist. Deshalb sollten alle hier vorfindlichen Empfehlungen stets im Kontext der jeweiligen Gegebenheiten betrachtet werden.\u0026nbsp;Beispielsweise ist die effektive Segmentierung des Netzwerks eine \u00e4u\u00dferst empfehlenswerte Ma\u00dfnahme, um die Ausbreitung von Ransomware einzud\u00e4mmen. Doch\u0026nbsp;wenn Ihrem Unternehmen nur ein begrenztes Budget zur Verf\u00fcgung steht, ist eine Kombination aus redundanten Ressourcen, Host-basierten Firewalls und allgemeinen H\u00e4rtungsma\u00dfnahmen m\u00f6glicherweise der Segmentierung mithilfe von Firewall-Appliances vorzuziehen.\u003C\/li\u003E\n\u003C\/ul\u003E\n",
        "jcr:lastModified": "Tue May 05 2020 22:36:34 GMT+0000",
        "sling:resourceType": "social\/blog\/components\/entrytext"
      }
    },
    "summary": {
      "jcr:primaryType": "nt:unstructured",
      "jcr:lastModifiedBy": "adam.greenberg@fireeye.com",
      "text": "\u003Cp\u003ENeue, auf Ransomware basierende Angriffsmethoden versetzen Cyberkriminelle in die Lage, industrielle Produktionsprozesse zu unterbrechen.\u003C\/p\u003E\n",
      "jcr:lastModified": "Mon Feb 24 2020 18:53:35 GMT+0000",
      "sling:resourceType": "social\/blog\/components\/entrytextteaser"
    },
    "image": {
      "jcr:primaryType": "nt:unstructured",
      "jcr:lastModifiedBy": "lynda.hall@fireeye.com",
      "jcr:lastModified": "Tue May 05 2020 22:33:51 GMT+0000",
      "imageRotate": "0"
    }
  }
}
